brc_pytorch/__init__.py
brc_pytorch/benchmarks.py
brc_pytorch/modules.py
brc_pytorch/utils.py
brc-0.1.2.dist-info/METADATA
brc-0.1.2.dist-info/WHEEL
brc-0.1.2.dist-info/top_level.txt
brc-0.1.2.dist-info/RECORD
