Metadata-Version: 2.1
Name: brc
Version: 0.1.2
Summary: Implementation of the bistable recurrent cell (BRC) in PyTorch
Home-page: https://github.com/kklemon/brc-pytorch
Author: Kristian Klemon
Author-email: kristian.klemon@gmail.com
License: MIT
Keywords: artificial intelligence,deep learning
Requires-Dist: torch
